starship_landing_gym/__init__.py
starship_landing_gym/envs/__init__.py
starship_landing_gym/envs/starship_env.py
starship_landing_gym/wrappers.py
starship_landing_gym-0.1.3.dist-info/WHEEL
starship_landing_gym-0.1.3.dist-info/METADATA
starship_landing_gym-0.1.3.dist-info/RECORD
