Metadata-Version: 2.1
Name: starship-landing-gym
Version: 0.1.3
Summary: A Gym env for rocket landing.
Home-page: https://github.com/Armandpl/starship-landing-gym
Author: Armandpl
Author-email: adpl33@gmail.com
Requires-Python: >=3.7.1,<3.10
Classifier: Programming Language :: Python :: 3
Classifier: Programming Language :: Python :: 3.8
Classifier: Programming Language :: Python :: 3.9
Requires-Dist: gym (==0.19.0)
Requires-Dist: numpy (==1.21.5)
Requires-Dist: pyglet (>=1.5.21,<2.0.0)
Requires-Dist: stable-baselines3 (>=1.4.0,<2.0.0)
Project-URL: Repository, https://github.com/Armandpl/starship-landing-gym
